trinpyqtt/__init__.py
trinpyqtt/client.py
trinpyqtt/demo/__init__.py
trinpyqtt/demo/raspidemo.py
trinpyqtt/models/__init__.py
trinpyqtt/models/raspberrypi.py
trinpyqtt/tools/__init__.py
trinpyqtt/tools/constants.py
trinpyqtt/tools/cryptools.py
trinpyqtt/tools/msgparser.py
trinpyqtt/tools/utils.py
trinpyqtt-0.14.0.dist-info/LICENSE
trinpyqtt-0.14.0.dist-info/METADATA
trinpyqtt-0.14.0.dist-info/WHEEL
trinpyqtt-0.14.0.dist-info/top_level.txt
trinpyqtt-0.14.0.dist-info/RECORD
