Metadata-Version: 2.1
Name: trinpyqtt
Version: 0.14.0
Summary: Trinity MQTT Tools for Python clients
Home-page: https://bitbucket.org/trintel/trinpyqtt
Author: Jan Badenhorst
Author-email: jan@trintel.co.za
License: MIT
Keywords: mqtt, raspberrypi
Platform: UNKNOWN
Classifier: Development Status :: 3 - Alpha
Classifier: Intended Audience :: Developers
Classifier: Programming Language :: Python :: 3.5
Classifier: Operating System :: POSIX :: Linux
Classifier: Topic :: Software Development :: Libraries :: Python Modules
Requires-Python: ~=3.5
License-File: LICENSE
Requires-Dist: pycryptodomex
Requires-Dist: psutil
Requires-Dist: paho-mqtt
